MANIFEST.in
README.md
setup.py
git_tessera.egg-info/PKG-INFO
git_tessera.egg-info/SOURCES.txt
git_tessera.egg-info/dependency_links.txt
git_tessera.egg-info/entry_points.txt
git_tessera.egg-info/requires.txt
git_tessera.egg-info/top_level.txt
tessera/__init__.py
tessera/exceptions.py
tessera/gitcommands.py
tessera/gittessera.py
tessera/main.py
tessera/mygit.py
tessera/tessera.py
tessera/tesseraconfig.py
tessera/tesseraweb.py
tessera/version.py
tessera/config/config
tessera/config/template
tessera/web/detail.html
tessera/web/index.html
tessera/web/style/tessera.css