Metadata-Version: 1.1
Name: git-tessera
Version: 0.00.02
Summary: manage your issues in your repository
Home-page: https://github.com/neolynx/git-tessera.git
Author: André Roth
Author-email: neolynx@gmail.com
License: GPL
Download-URL: https://github.com/neolynx/git-tessera.git
Platform: Linux
Platform: Windows
Platform: MAC OS X
Classifier: Development Status :: 4 - Beta
Classifier: Environment :: Console
Classifier: Intended Audience :: Developers
Classifier: Intended Audience :: Education
Classifier: Intended Audience :: Other Audience
Classifier: License :: OSI Approved :: GNU General Public License v3 (GPLv3)
Classifier: Natural Language :: English
Classifier: Operating System :: MacOS :: MacOS X
Classifier: Operating System :: OS Independent
Classifier: Operating System :: Microsoft :: Windows
Classifier: Operating System :: Microsoft :: Windows :: Windows 7
Classifier: Operating System :: Microsoft :: Windows :: Windows XP
Classifier: Operating System :: POSIX
Classifier: Operating System :: POSIX :: Linux
Classifier: Programming Language :: Python
Classifier: Programming Language :: Python :: 2.6
Classifier: Programming Language :: Python :: 2.7
Classifier: Programming Language :: Python :: 3
Classifier: Programming Language :: Python :: 3.2
Classifier: Programming Language :: Python :: Implementation
Classifier: Topic :: Education :: Testing
Classifier: Topic :: Software Development
Classifier: Topic :: Software Development :: Testing
